{"v":"5.3.4","fr":59.9819946289063,"ip":0,"op":60.9999945377493,"w":602,"h":680,"nm":"HeartMan","ddd":0,"assets":[],"layers":[{"ddd":0,"ind":1,"ty":4,"nm":"butt","parent":37,"sr":1,"ks":{"o":{"a":0,"k":100,"ix":11},"r":{"a":0,"k":-8.141,"ix":10},"p":{"a":0,"k":[32.327,56.547,0],"ix":2},"a":{"a":0,"k":[0,0,0],"ix":1},"s":{"a":0,"k":[104.043,96.272,100],"ix":6}},"ao":0,"shapes":[{"ty":"gr","it":[{"ind":0,"ty":"sh","ix":1,"ks":{"a":0,"k":{"i":[[12.5,-9],[-39.313,-14.609],[-21.5,-5.5],[-19.312,-5.909],[0,0],[53,11]],"o":[[-9.221,6.639],[22.071,8.202],[20.051,5.129],[28.947,8.857],[0,0],[-53,-11]],"v":[[-56.343,-42.973],[-64.571,59.798],[-4,82.5],[51.812,98.909],[103.335,-6.267],[18,-10]],"c":true},"ix":2},"nm":"Path 1","mn":"ADBE Vector Shape - Group","hd":false},{"ty":"st","c":{"a":0,"k":[1,0.869804053213,0.776471007104,1],"ix":3},"o":{"a":0,"k":100,"ix":4},"w":{"a":0,"k":0,"ix":5},"lc":1,"lj":1,"ml":4,"ml2":{"a":0,"k":4,"ix":8},"nm":"Stroke 1","mn":"ADBE Vector Graphic - Stroke","hd":false},{"ty":"fl","c":{"a":0,"k":[0.23137254902,0.149019607843,0.349019607843,1],"ix":4},"o":{"a":0,"k":100,"ix":5},"r":1,"nm":"Fill 1","mn":"ADBE Vector Graphic - Fill","hd":false},{"ty":"tr","p":{"a":0,"k":[0,0],"ix":2},"a":{"a":0,"k":[0,0],"ix":1},"s":{"a":0,"k":[100,100],"ix":3},"r":{"a":0,"k":0,"ix":6},"o":{"a":0,"k":100,"ix":7},"sk":{"a":0,"k":0,"ix":4},"sa":{"a":0,"k":0,"ix":5},"nm":"Transform"}],"nm":"Shape 1","np":3,"cix":2,"ix":1,"mn":"ADBE Vector Group","hd":false}],"ip":0,"op":60.9999945377493,"st":0,"bm":0},{"ddd":0,"ind":2,"ty":4,"nm":"pants_f","parent":37,"sr":1,"ks":{"o":{"a":0,"k":100,"ix":11},"r":{"a":1,"k":[{"i":{"x":[0.667],"y":[1]},"o":{"x":[0.333],"y":[0]},"n":["0p667_1_0p333_0"],"t":-1,"s":[141],"e":[44]},{"i":{"x":[0.667],"y":[0.764]},"o":{"x":[0.333],"y":[0]},"n":["0p667_0p764_0p333_0"],"t":14,"s":[44],"e":[-0.253]},{"i":{"x":[0.667],"y":[1]},"o":{"x":[0.333],"y":[16]},"n":["0p667_1_0p333_16"],"t":21,"s":[-0.253],"e":[-1]},{"i":{"x":[0.667],"y":[0.131]},"o":{"x":[0.333],"y":[0]},"n":["0p667_0p131_0p333_0"],"t":29,"s":[-1],"e":[17.635]},{"i":{"x":[0.667],"y":[1]},"o":{"x":[0.333],"y":[0.334]},"n":["0p667_1_0p333_0p334"],"t":37,"s":[17.635],"e":[60]},{"i":{"x":[0.667],"y":[1]},"o":{"x":[0.333],"y":[0]},"n":["0p667_1_0p333_0"],"t":44,"s":[60],"e":[141]},{"t":59.9999946272944}],"ix":10},"p":{"a":0,"k":[13.736,103.849,0],"ix":2},"a":{"a":0,"k":[124.829,78.563,0],"ix":1},"s":{"a":0,"k":[97.087,103.093,100],"ix":6}},"ao":0,"shapes":[{"ty":"gr","it":[{"ind":0,"ty":"sh","ix":1,"ks":{"a":0,"k":{"i":[[17.183,-6.949],[8.313,-19.865],[-16.168,-18.427],[-23.354,-6.292],[13.26,19.006]],"o":[[-33.376,13.498],[-7.213,17.236],[17.997,20.511],[77.154,20.786],[-15,-21.5]],"v":[[123.876,34.002],[80.687,62.865],[90.503,121.989],[141.341,145.851],[198.25,45.5]],"c":true},"ix":2},"nm":"Path 1","mn":"ADBE Vector Shape - Group","hd":false},{"ty":"st","c":{"a":0,"k":[1,0.869804053213,0.776471007104,1],"ix":3},"o":{"a":0,"k":100,"ix":4},"w":{"a":0,"k":0,"ix":5},"lc":1,"lj":1,"ml":4,"ml2":{"a":0,"k":4,"ix":8},"nm":"Stroke 1","mn":"ADBE Vector Graphic - Stroke","hd":false},{"ty":"fl","c":{"a":0,"k":[0.23137254902,0.149019607843,0.349019607843,1],"ix":4},"o":{"a":0,"k":100,"ix":5},"r":1,"nm":"Fill 1","mn":"ADBE Vector Graphic - Fill","hd":false},{"ty":"tr","p":{"a":0,"k":[0,0],"ix":2},"a":{"a":0,"k":[0,0],"ix":1},"s":{"a":0,"k":[100,100],"ix":3},"r":{"a":0,"k":0,"ix":6},"o":{"a":0,"k":100,"ix":7},"sk":{"a":0,"k":0,"ix":4},"sa":{"a":0,"k":0,"ix":5},"nm":"Transform"}],"nm":"Shape 1","np":3,"cix":2,"ix":1,"mn":"ADBE Vector Group","hd":false}],"ip":0,"op":60.9999945377493,"st":0,"bm":0},{"ddd":0,"ind":3,"ty":4,"nm":"upperleg_f","parent":2,"sr":1,"ks":{"o":{"a":0,"k":100,"ix":11},"r":{"a":0,"k":0,"ix":10},"p":{"a":0,"k":[118.263,84.185,0],"ix":2},"a":{"a":0,"k":[118.263,84.185,0],"ix":1},"s":{"a":0,"k":[100,100,100],"ix":6}},"ao":0,"shapes":[{"ty":"gr","it":[{"ind":0,"ty":"sh","ix":1,"ks":{"a":0,"k":{"i":[[0,0],[0,0],[-9.5,-1.75],[-1,4.5],[7,3]],"o":[[0,0],[0,0],[9.5,1.75],[1,-4.5],[-7,-3]],"v":[[114.5,76.5],[107,87],[240.75,110.25],[251.75,102],[245.25,94.5]],"c":true},"ix":2},"nm":"Path 1","mn":"ADBE Vector Shape - Group","hd":false},{"ty":"st","c":{"a":0,"k":[1,0.869804053213,0.776471007104,1],"ix":3},"o":{"a":0,"k":100,"ix":4},"w":{"a":0,"k":0,"ix":5},"lc":1,"lj":1,"ml":4,"ml2":{"a":0,"k":4,"ix":8},"nm":"Stroke 1","mn":"ADBE Vector Graphic - Stroke","hd":false},{"ty":"fl","c":{"a":0,"k":[0.23137254902,0.149019607843,0.349019607843,1],"ix":4},"o":{"a":0,"k":100,"ix":5},"r":1,"nm":"Fill 1","mn":"ADBE Vector Graphic - Fill","hd":false},{"ty":"tr","p":{"a":0,"k":[0,0],"ix":2},"a":{"a":0,"k":[0,0],"ix":1},"s":{"a":0,"k":[100,100],"ix":3},"r":{"a":0,"k":0,"ix":6},"o":{"a":0,"k":100,"ix":7},"sk":{"a":0,"k":0,"ix":4},"sa":{"a":0,"k":0,"ix":5},"nm":"Transform"}],"nm":"Shape 1","np":3,"cix":2,"ix":1,"mn":"ADBE Vector Group","hd":false}],"ip":0,"op":60.9999945377493,"st":0,"bm":0},{"ddd":0,"ind":4,"ty":4,"nm":"calf_f","parent":3,"sr":1,"ks":{"o":{"a":0,"k":100,"ix":11},"r":{"a":1,"k":[{"i":{"x":[0.667],"y":[1]},"o":{"x":[0.333],"y":[0]},"n":["0p667_1_0p333_0"],"t":2,"s":[0],"e":[24.429]},{"i":{"x":[0.667],"y":[1]},"o":{"x":[0.333],"y":[0]},"n":["0p667_1_0p333_0"],"t":14,"s":[24.429],"e":[-39.786]},{"i":{"x":[0.667],"y":[1.599]},"o":{"x":[0.333],"y":[0]},"n":["0p667_1p599_0p333_0"],"t":29,"s":[-39.786],"e":[-25.501]},{"i":{"x":[0.667],"y":[1]},"o":{"x":[0.333],"y":[0.161]},"n":["0p667_1_0p333_0p161"],"t":37,"s":[-25.501],"e":[-72]},{"i":{"x":[0.667],"y":[0.851]},"o":{"x":[0.333],"y":[0]},"n":["0p667_0p851_0p333_0"],"t":44,"s":[-72],"e":[-7.301]},{"i":{"x":[0.667],"y":[1]},"o":{"x":[0.333],"y":[2.913]},"n":["0p667_1_0p333_2p913"],"t":49,"s":[-7.301],"e":[0]},{"t":59.9999946272944}],"ix":10},"p":{"a":0,"k":[246,101.25,0],"ix":2},"a":{"a":0,"k":[246,101.25,0],"ix":1},"s":{"a":0,"k":[100,100,100],"ix":6}},"ao":0,"shapes":[{"ty":"gr","it":[{"ind":0,"ty":"sh","ix":1,"ks":{"a":0,"k":{"i":[[6.375,0.5],[-0.25,-8.5],[0,0],[-4.5,-0.5],[0,0],[0.474,11.375]],"o":[[-4.985,-0.391],[0.25,8.5],[0,0],[4.5,0.5],[0,0],[-0.375,-9]],"v":[[245.75,96.125],[240.25,112.375],[242,155.5],[246,160.75],[249.75,155.5],[251.625,110.75]],"c":true},"ix":2},"nm":"Path 1","mn":"ADBE Vector Shape - Group","hd":false},{"ty":"st","c":{"a":0,"k":[1,0.869804053213,0.776471007104,1],"ix":3},"o":{"a":0,"k":100,"ix":4},"w":{"a":0,"k":0,"ix":5},"lc":1,"lj":1,"ml":4,"ml2":{"a":0,"k":4,"ix":8},"nm":"Stroke 1","mn":"ADBE Vector Graphic - Stroke","hd":false},{"ty":"fl","c":{"a":0,"k":[0.23137254902,0.149019607843,0.349019607843,1],"ix":4},"o":{"a":0,"k":100,"ix":5},"r":1,"nm":"Fill 1","mn":"ADBE Vector Graphic - Fill","hd":false},{"ty":"tr","p":{"a":0,"k":[0,0],"ix":2},"a":{"a":0,"k":[0,0],"ix":1},"s":{"a":0,"k":[100,100],"ix":3},"r":{"a":0,"k":0,"ix":6},"o":{"a":0,"k":100,"ix":7},"sk":{"a":0,"k":0,"ix":4},"sa":{"a":0,"k":0,"ix":5},"nm":"Transform"}],"nm":"Shape 1","np":3,"cix":2,"ix":1,"mn":"ADBE Vector Group","hd":false}],"ip":0,"op":60.9999945377493,"st":0,"bm":0},{"ddd":0,"ind":5,"ty":4,"nm":"foot_f","parent":4,"sr":1,"ks":{"o":{"a":0,"k":100,"ix":11},"r":{"a":1,"k":[{"i":{"x":[0.833],"y":[1]},"o":{"x":[0.333],"y":[0]},"n":["0p833_1_0p333_0"],"t":1,"s":[0],"e":[41]},{"i":{"x":[0.737],"y":[0.981]},"o":{"x":[0.159],"y":[0]},"n":["0p737_0p981_0p159_0"],"t":17,"s":[41],"e":[4.17]},{"i":{"x":[0.752],"y":[1]},"o":{"x":[0.411],"y":[-0.007]},"n":["0p752_1_0p411_-0p007"],"t":27,"s":[4.17],"e":[37]},{"i":{"x":[0.833],"y":[1]},"o":{"x":[0.167],"y":[0]},"n":["0p833_1_0p167_0"],"t":29,"s":[37],"e":[1]},{"t":36.9999966868316}],"ix":10},"p":{"a":0,"k":[246.188,157.813,0],"ix":2},"a":{"a":0,"k":[246.187,157.813,0],"ix":1},"s":{"a":0,"k":[100,100,100],"ix":6}},"ao":0,"shapes":[{"ty":"gr","it":[{"ind":0,"ty":"sh","ix":1,"ks":{"a":0,"k":{"i":[[2.875,-0.375],[0,0],[0,0],[0,0],[0,0]],"o":[[-2.875,0.375],[0,0],[0,0],[0,0],[0,0]],"v":[[246.125,154.75],[242.375,158.375],[242.25,168],[268.25,168],[250.125,159]],"c":true},"ix":2},"nm":"Path 1","mn":"ADBE Vector Shape - Group","hd":false},{"ty":"st","c":{"a":0,"k":[1,0.869804053213,0.776471007104,1],"ix":3},"o":{"a":0,"k":100,"ix":4},"w":{"a":0,"k":0,"ix":5},"lc":1,"lj":1,"ml":4,"ml2":{"a":0,"k":4,"ix":8},"nm":"Stroke 1","mn":"ADBE Vector Graphic - Stroke","hd":false},{"ty":"fl","c":{"a":0,"k":[0.23137254902,0.149019607843,0.349019607843,1],"ix":4},"o":{"a":0,"k":100,"ix":5},"r":1,"nm":"Fill 1","mn":"ADBE Vector Graphic - Fill","hd":false},{"ty":"tr","p":{"a":0,"k":[0,0],"ix":2},"a":{"a":0,"k":[0,0],"ix":1},"s":{"a":0,"k":[100,100],"ix":3},"r":{"a":0,"k":0,"ix":6},"o":{"a":0,"k":100,"ix":7},"sk":{"a":0,"k":0,"ix":4},"sa":{"a":0,"k":0,"ix":5},"nm":"Transform"}],"nm":"Shape 1","np":3,"cix":2,"ix":1,"mn":"ADBE Vector Group","hd":false}],"ip":0,"op":60.9999945377493,"st":0,"bm":0},{"ddd":0,"ind":6,"ty":4,"nm":"pants_b","parent":37,"sr":1,"ks":{"o":{"a":0,"k":100,"ix":11},"r":{"a":1,"k":[{"i":{"x":[0.667],"y":[0.269]},"o":{"x":[0.333],"y":[0]},"n":["0p667_0p269_0p333_0"],"t":0,"s":[0],"e":[26.528]},{"i":{"x":[0.667],"y":[1]},"o":{"x":[0.333],"y":[0.347]},"n":["0p667_1_0p333_0p347"],"t":9,"s":[26.528],"e":[70]},{"i":{"x":[0.667],"y":[0.595]},"o":{"x":[0.333],"y":[0]},"n":["0p667_0p595_0p333_0"],"t":16,"s":[70],"e":[86.514]},{"i":{"x":[0.667],"y":[1]},"o":{"x":[0.333],"y":[0.436]},"n":["0p667_1_0p333_0p436"],"t":20,"s":[86.514],"e":[121]},{"i":{"x":[0.667],"y":[1]},"o":{"x":[0.333],"y":[0]},"n":["0p667_1_0p333_0"],"t":29,"s":[121],"e":[-7]},{"i":{"x":[0.667],"y":[1]},"o":{"x":[0.333],"y":[0]},"n":["0p667_1_0p333_0"],"t":44,"s":[-7],"e":[0]},{"t":59.9999946272944}],"ix":10},"p":{"a":0,"k":[121.503,85.293,0],"ix":2},"a":{"a":0,"k":[124.829,78.563,0],"ix":1},"s":{"a":0,"k":[97.087,103.093,100],"ix":6}},"ao":0,"shapes":[{"ty":"gr","it":[{"ind":0,"ty":"sh","ix":1,"ks":{"a":0,"k":{"i":[[17.183,-6.949],[8.313,-19.865],[-16.168,-18.427],[-23.354,-6.292],[13.26,19.006]],"o":[[-33.376,13.498],[-7.213,17.236],[17.997,20.511],[77.154,20.786],[-15,-21.5]],"v":[[123.876,34.002],[80.687,62.865],[90.503,121.989],[141.341,145.851],[198.25,45.5]],"c":true},"ix":2},"nm":"Path 1","mn":"ADBE Vector Shape - Group","hd":false},{"ty":"st","c":{"a":0,"k":[1,0.869804053213,0.776471007104,1],"ix":3},"o":{"a":0,"k":100,"ix":4},"w":{"a":0,"k":0,"ix":5},"lc":1,"lj":1,"ml":4,"ml2":{"a":0,"k":4,"ix":8},"nm":"Stroke 1","mn":"ADBE Vector Graphic - Stroke","hd":false},{"ty":"fl","c":{"a":0,"k":[0.23137254902,0.149019607843,0.349019607843,1],"ix":4},"o":{"a":0,"k":100,"ix":5},"r":1,"nm":"Fill 1","mn":"ADBE Vector Graphic - Fill","hd":false},{"ty":"tr","p":{"a":0,"k":[0,0],"ix":2},"a":{"a":0,"k":[0,0],"ix":1},"s":{"a":0,"k":[100,100],"ix":3},"r":{"a":0,"k":0,"ix":6},"o":{"a":0,"k":100,"ix":7},"sk":{"a":0,"k":0,"ix":4},"sa":{"a":0,"k":0,"ix":5},"nm":"Transform"}],"nm":"Shape 1","np":3,"cix":2,"ix":1,"mn":"ADBE Vector Group","hd":false}],"ip":0,"op":60.9999945377493,"st":0,"bm":0},{"ddd":0,"ind":7,"ty":4,"nm":"upperleg_b","parent":6,"sr":1,"ks":{"o":{"a":0,"k":100,"ix":11},"r":{"a":0,"k":0,"ix":10},"p":{"a":0,"k":[118.263,84.185,0],"ix":2},"a":{"a":0,"k":[118.263,84.185,0],"ix":1},"s":{"a":0,"k":[100,100,100],"ix":6}},"ao":0,"shapes":[{"ty":"gr","it":[{"ind":0,"ty":"sh","ix":1,"ks":{"a":0,"k":{"i":[[0,0],[0,0],[-9.5,-1.75],[-1,4.5],[7,3]],"o":[[0,0],[0,0],[9.5,1.75],[1,-4.5],[-7,-3]],"v":[[114.5,76.5],[107,87],[240.75,110.25],[251.75,102],[245.25,94.5]],"c":true},"ix":2},"nm":"Path 1","mn":"ADBE Vector Shape - Group","hd":false},{"ty":"st","c":{"a":0,"k":[1,0.869804053213,0.776471007104,1],"ix":3},"o":{"a":0,"k":100,"ix":4},"w":{"a":0,"k":0,"ix":5},"lc":1,"lj":1,"ml":4,"ml2":{"a":0,"k":4,"ix":8},"nm":"Stroke 1","mn":"ADBE Vector Graphic - Stroke","hd":false},{"ty":"fl","c":{"a":0,"k":[0.23137254902,0.149019607843,0.349019607843,1],"ix":4},"o":{"a":0,"k":100,"ix":5},"r":1,"nm":"Fill 1","mn":"ADBE Vector Graphic - Fill","hd":false},{"ty":"tr","p":{"a":0,"k":[0,0],"ix":2},"a":{"a":0,"k":[0,0],"ix":1},"s":{"a":0,"k":[100,100],"ix":3},"r":{"a":0,"k":0,"ix":6},"o":{"a":0,"k":100,"ix":7},"sk":{"a":0,"k":0,"ix":4},"sa":{"a":0,"k":0,"ix":5},"nm":"Transform"}],"nm":"Shape 1","np":3,"cix":2,"ix":1,"mn":"ADBE Vector Group","hd":false}],"ip":0,"op":60.9999945377493,"st":0,"bm":0},{"ddd":0,"ind":8,"ty":4,"nm":"calf_b","parent":7,"sr":1,"ks":{"o":{"a":0,"k":100,"ix":11},"r":{"a":1,"k":[{"i":{"x":[0.667],"y":[1]},"o":{"x":[0.333],"y":[0]},"n":["0p667_1_0p333_0"],"t":1,"s":[0],"e":[-72]},{"i":{"x":[0.667],"y":[0.85]},"o":{"x":[0.333],"y":[0]},"n":["0p667_0p85_0p333_0"],"t":16,"s":[-72],"e":[-24.809]},{"i":{"x":[0.667],"y":[1]},"o":{"x":[0.333],"y":[2.339]},"n":["0p667_1_0p333_2p339"],"t":20,"s":[-24.809],"e":[-18]},{"i":{"x":[0.667],"y":[1]},"o":{"x":[0.333],"y":[0]},"n":["0p667_1_0p333_0"],"t":29,"s":[-18],"e":[57]},{"i":{"x":[0.667],"y":[1]},"o":{"x":[0.333],"y":[0]},"n":["0p667_1_0p333_0"],"t":46,"s":[57],"e":[0]},{"t":59.9999946272944}],"ix":10},"p":{"a":0,"k":[246,101.25,0],"ix":2},"a":{"a":0,"k":[246,101.25,0],"ix":1},"s":{"a":0,"k":[100,100,100],"ix":6}},"ao":0,"shapes":[{"ty":"gr","it":[{"ind":0,"ty":"sh","ix":1,"ks":{"a":0,"k":{"i":[[6.375,0.5],[-0.25,-8.5],[0,0],[-4.5,-0.5],[0,0],[0.474,11.375]],"o":[[-4.985,-0.391],[0.25,8.5],[0,0],[4.5,0.5],[0,0],[-0.375,-9]],"v":[[245.75,96.125],[240.25,112.375],[242,155.5],[246,160.75],[249.75,155.5],[251.625,110.75]],"c":true},"ix":2},"nm":"Path 1","mn":"ADBE Vector Shape - Group","hd":false},{"ty":"st","c":{"a":0,"k":[1,0.869804053213,0.776471007104,1],"ix":3},"o":{"a":0,"k":100,"ix":4},"w":{"a":0,"k":0,"ix":5},"lc":1,"lj":1,"ml":4,"ml2":{"a":0,"k":4,"ix":8},"nm":"Stroke 1","mn":"ADBE Vector Graphic - Stroke","hd":false},{"ty":"fl","c":{"a":0,"k":[0.23137254902,0.149019607843,0.349019607843,1],"ix":4},"o":{"a":0,"k":100,"ix":5},"r":1,"nm":"Fill 1","mn":"ADBE Vector Graphic - Fill","hd":false},{"ty":"tr","p":{"a":0,"k":[0,0],"ix":2},"a":{"a":0,"k":[0,0],"ix":1},"s":{"a":0,"k":[100,100],"ix":3},"r":{"a":0,"k":0,"ix":6},"o":{"a":0,"k":100,"ix":7},"sk":{"a":0,"k":0,"ix":4},"sa":{"a":0,"k":0,"ix":5},"nm":"Transform"}],"nm":"Shape 1","np":3,"cix":2,"ix":1,"mn":"ADBE Vector Group","hd":false}],"ip":0,"op":60.9999945377493,"st":0,"bm":0},{"ddd":0,"ind":9,"ty":4,"nm":"foot_b","parent":8,"sr":1,"ks":{"o":{"a":0,"k":100,"ix":11},"r":{"a":1,"k":[{"i":{"x":[0.833],"y":[1]},"o":{"x":[0.333],"y":[0]},"n":["0p833_1_0p333_0"],"t":0,"s":[0],"e":[32]},{"i":{"x":[0.833],"y":[1]},"o":{"x":[0.167],"y":[0]},"n":["0p833_1_0p167_0"],"t":33,"s":[32],"e":[-38]},{"i":{"x":[0.667],"y":[1]},"o":{"x":[0.167],"y":[0]},"n":["0p667_1_0p167_0"],"t":57,"s":[-38],"e":[0]},{"t":59.9999946272944}],"ix":10},"p":{"a":0,"k":[246.188,157.813,0],"ix":2},"a":{"a":0,"k":[246.187,157.813,0],"ix":1},"s":{"a":0,"k":[100,100,100],"ix":6}},"ao":0,"shapes":[{"ty":"gr","it":[{"ind":0,"ty":"sh","ix":1,"ks":{"a":0,"k":{"i":[[2.875,-0.375],[0,0],[0,0],[0,0],[0,0]],"o":[[-2.875,0.375],[0,0],[0,0],[0,0],[0,0]],"v":[[246.125,154.75],[242.375,158.375],[242.25,168],[268.25,168],[250.125,159]],"c":true},"ix":2},"nm":"Path 1","mn":"ADBE Vector Shape - Group","hd":false},{"ty":"st","c":{"a":0,"k":[1,0.869804053213,0.776471007104,1],"ix":3},"o":{"a":0,"k":100,"ix":4},"w":{"a":0,"k":0,"ix":5},"lc":1,"lj":1,"ml":4,"ml2":{"a":0,"k":4,"ix":8},"nm":"Stroke 1","mn":"ADBE Vector Graphic - Stroke","hd":false},{"ty":"fl","c":{"a":0,"k":[0.23137254902,0.149019607843,0.349019607843,1],"ix":4},"o":{"a":0,"k":100,"ix":5},"r":1,"nm":"Fill 1","mn":"ADBE Vector Graphic - Fill","hd":false},{"ty":"tr","p":{"a":0,"k":[0,0],"ix":2},"a":{"a":0,"k":[0,0],"ix":1},"s":{"a":0,"k":[100,100],"ix":3},"r":{"a":0,"k":0,"ix":6},"o":{"a":0,"k":100,"ix":7},"sk":{"a":0,"k":0,"ix":4},"sa":{"a":0,"k":0,"ix":5},"nm":"Transform"}],"nm":"Shape 1","np":3,"cix":2,"ix":1,"mn":"ADBE Vector Group","hd":false}],"ip":0,"op":60.9999945377493,"st":0,"bm":0},{"ddd":0,"ind":10,"ty":4,"nm":"skirtLine1","parent":13,"sr":1,"ks":{"o":{"a":0,"k":100,"ix":11},"r":{"a":0,"k":0,"ix":10},"p":{"a":0,"k":[-33,65.5,0],"ix":2},"a":{"a":0,"k":[-33,65.5,0],"ix":1},"s":{"a":0,"k":[100,100,100],"ix":6}},"ao":0,"shapes":[{"ty":"gr","it":[{"ind":0,"ty":"sh","ix":1,"ks":{"a":0,"k":{"i":[[0,0],[0,0]],"o":[[0,0],[0,0]],"v":[[-29.5,61.5],[-36.5,69.5]],"c":false},"ix":2},"nm":"Path 1","mn":"ADBE Vector Shape - Group","hd":false},{"ty":"st","c":{"a":0,"k":[0.88671875,0.828125,1,1],"ix":3},"o":{"a":0,"k":100,"ix":4},"w":{"a":0,"k":2,"ix":5},"lc":1,"lj":1,"ml":10,"ml2":{"a":0,"k":10,"ix":8},"nm":"Stroke 1","mn":"ADBE Vector Graphic - Stroke","hd":false},{"ty":"tr","p":{"a":0,"k":[0,0],"ix":2},"a":{"a":0,"k":[0,0],"ix":1},"s":{"a":0,"k":[100,100],"ix":3},"r":{"a":0,"k":0,"ix":6},"o":{"a":0,"k":100,"ix":7},"sk":{"a":0,"k":0,"ix":4},"sa":{"a":0,"k":0,"ix":5},"nm":"Transform"}],"nm":"Group 1","np":2,"cix":2,"ix":1,"mn":"ADBE Vector Group","hd":false}],"ip":0,"op":60.9999945377493,"st":0,"bm":0},{"ddd":0,"ind":11,"ty":4,"nm":"skirtLine2","parent":13,"sr":1,"ks":{"o":{"a":0,"k":100,"ix":11},"r":{"a":0,"k":0,"ix":10},"p":{"a":0,"k":[-40,55.5,0],"ix":2},"a":{"a":0,"k":[-40,55.5,0],"ix":1},"s":{"a":0,"k":[100,100,100],"ix":6}},"ao":0,"shapes":[{"ty":"gr","it":[{"ind":0,"ty":"sh","ix":1,"ks":{"a":0,"k":{"i":[[0,0],[0,0]],"o":[[0,0],[0,0]],"v":[[-26.5,47.5],[-53.5,63.5]],"c":false},"ix":2},"nm":"Path 1","mn":"ADBE Vector Shape - Group","hd":false},{"ty":"st","c":{"a":0,"k":[0.88671875,0.828125,1,1],"ix":3},"o":{"a":0,"k":100,"ix":4},"w":{"a":0,"k":2,"ix":5},"lc":1,"lj":1,"ml":10,"ml2":{"a":0,"k":10,"ix":8},"nm":"Stroke 1","mn":"ADBE Vector Graphic - Stroke","hd":false},{"ty":"tr","p":{"a":0,"k":[0,0],"ix":2},"a":{"a":0,"k":[0,0],"ix":1},"s":{"a":0,"k":[100,100],"ix":3},"r":{"a":0,"k":0,"ix":6},"o":{"a":0,"k":100,"ix":7},"sk":{"a":0,"k":0,"ix":4},"sa":{"a":0,"k":0,"ix":5},"nm":"Transform"}],"nm":"Group 1","np":2,"cix":2,"ix":1,"mn":"ADBE Vector Group","hd":false}],"ip":0,"op":60.9999945377493,"st":0,"bm":0},{"ddd":0,"ind":12,"ty":4,"nm":"belt","parent":13,"sr":1,"ks":{"o":{"a":0,"k":100,"ix":11},"r":{"a":0,"k":0,"ix":10},"p":{"a":0,"k":[50,45.093,0],"ix":2},"a":{"a":0,"k":[50,45.093,0],"ix":1},"s":{"a":0,"k":[100,100,100],"ix":6}},"ao":0,"shapes":[{"ty":"gr","it":[{"ind":0,"ty":"sh","ix":1,"ks":{"a":0,"k":{"i":[[0,0],[0,0],[-56.927,-2.274],[0,0],[0,0],[61.106,-1.587]],"o":[[0,0],[0,0],[56.927,2.274],[0,0],[0,0],[-70.033,1.819]],"v":[[-39.978,12.395],[-30.967,27.644],[48.45,54.351],[134.509,44.039],[145.929,16.992],[68.743,27.912]],"c":true},"ix":2},"nm":"Path 1","mn":"ADBE Vector Shape - Group","hd":false},{"ty":"fl","c":{"a":0,"k":[0.701960784314,0.619607843137,0.898039215686,1],"ix":4},"o":{"a":0,"k":100,"ix":5},"r":1,"nm":"Fill 1","mn":"ADBE Vector Graphic - Fill","hd":false},{"ty":"tr","p":{"a":0,"k":[0,0],"ix":2},"a":{"a":0,"k":[0,0],"ix":1},"s":{"a":0,"k":[100,100],"ix":3},"r":{"a":0,"k":0,"ix":6},"o":{"a":0,"k":100,"ix":7},"sk":{"a":0,"k":0,"ix":4},"sa":{"a":0,"k":0,"ix":5},"nm":"Transform"}],"nm":"Group 1","np":2,"cix":2,"ix":1,"mn":"ADBE Vector Group","hd":false}],"ip":0,"op":60.9999945377493,"st":0,"bm":0},{"ddd":0,"ind":13,"ty":3,"nm":"skirt","parent":37,"sr":1,"ks":{"o":{"a":0,"k":100,"ix":11},"r":{"a":1,"k":[{"i":{"x":[0.667],"y":[1]},"o":{"x":[0.333],"y":[0]},"n":["0p667_1_0p333_0"],"t":0,"s":[0],"e":[2]},{"i":{"x":[0.667],"y":[1]},"o":{"x":[0.333],"y":[0]},"n":["0p667_1_0p333_0"],"t":16,"s":[2],"e":[-5]},{"i":{"x":[0.667],"y":[1]},"o":{"x":[0.333],"y":[0]},"n":["0p667_1_0p333_0"],"t":33,"s":[-5],"e":[1]},{"i":{"x":[0.667],"y":[1]},"o":{"x":[0.333],"y":[0]},"n":["0p667_1_0p333_0"],"t":51,"s":[1],"e":[0]},{"t":59.9999946272944}],"ix":10},"p":{"a":0,"k":[50.013,52.053,0],"ix":2},"a":{"a":0,"k":[47.513,56.553,0],"ix":1},"s":{"a":0,"k":[100,100,100],"ix":6}},"ao":0,"ip":0,"op":60.9999945377493,"st":0,"bm":0},{"ddd":0,"ind":14,"ty":4,"nm":"hand2","parent":15,"sr":1,"ks":{"o":{"a":0,"k":100,"ix":11},"r":{"a":0,"k":0,"ix":10},"p":{"a":0,"k":[-189.849,0.5,0],"ix":2},"a":{"a":0,"k":[-189.849,0.5,0],"ix":1},"s":{"a":0,"k":[100,100,100],"ix":6}},"ao":0,"shapes":[{"ty":"gr","it":[{"ind":0,"ty":"sh","ix":1,"ks":{"a":0,"k":{"i":[[0,0],[1,-16],[0,0],[1,23],[-3,-10],[0,0],[1,12],[0,0],[-1,-8],[0,0],[13,11],[0,0]],"o":[[0,0],[-1,16],[0,0],[0,0],[3,10],[0,0],[-1,-12],[0,0],[1,8],[0,0],[-12.07,-10.213],[0,0]],"v":[[-206.5,-27.5],[-202.5,0.5],[-213.5,21.5],[-194.5,-4.5],[-186.5,7.5],[-194.5,28.5],[-178.5,9.5],[-185.5,-6.5],[-173.5,9.5],[-173.5,24.5],[-171.5,-6.5],[-185.5,-24.5]],"c":true},"ix":2},"nm":"Path 1","mn":"ADBE Vector Shape - Group","hd":false},{"ty":"fl","c":{"a":0,"k":[0.23137254902,0.149019607843,0.349019607843,1],"ix":4},"o":{"a":0,"k":100,"ix":5},"r":1,"nm":"Fill 1","mn":"ADBE Vector Graphic - Fill","hd":false},{"ty":"tr","p":{"a":0,"k":[0,0],"ix":2},"a":{"a":0,"k":[0,0],"ix":1},"s":{"a":0,"k":[100,100],"ix":3},"r":{"a":0,"k":0,"ix":6},"o":{"a":0,"k":100,"ix":7},"sk":{"a":0,"k":0,"ix":4},"sa":{"a":0,"k":0,"ix":5},"nm":"Transform"}],"nm":"Group 1","np":2,"cix":2,"ix":1,"mn":"ADBE Vector Group","hd":false}],"ip":0,"op":60.9999945377493,"st":0,"bm":0},{"ddd":0,"ind":15,"ty":4,"nm":"arm2line2","parent":16,"sr":1,"ks":{"o":{"a":0,"k":100,"ix":11},"r":{"a":0,"k":0,"ix":10},"p":{"a":0,"k":[-121,-28.349,0],"ix":2},"a":{"a":0,"k":[-121,-28.349,0],"ix":1},"s":{"a":0,"k":[100,100,100],"ix":6}},"ao":0,"shapes":[{"ty":"gr","it":[{"ind":0,"ty":"sh","ix":1,"ks":{"a":0,"k":{"i":[[0,0],[-93,-74]],"o":[[0,0],[0,0]],"v":[[-188.5,-20.5],[-53.5,-10.5]],"c":false},"ix":2},"nm":"Path 1","mn":"ADBE Vector Shape - Group","hd":false},{"ty":"st","c":{"a":0,"k":[0.23137254902,0.149019607843,0.349019607843,1],"ix":3},"o":{"a":0,"k":100,"ix":4},"w":{"a":0,"k":4,"ix":5},"lc":1,"lj":1,"ml":10,"ml2":{"a":0,"k":10,"ix":8},"nm":"Stroke 1","mn":"ADBE Vector Graphic - Stroke","hd":false},{"ty":"tr","p":{"a":0,"k":[0,0],"ix":2},"a":{"a":0,"k":[0,0],"ix":1},"s":{"a":0,"k":[100,100],"ix":3},"r":{"a":0,"k":0,"ix":6},"o":{"a":0,"k":100,"ix":7},"sk":{"a":0,"k":0,"ix":4},"sa":{"a":0,"k":0,"ix":5},"nm":"Transform"}],"nm":"Group 1","np":2,"cix":2,"ix":1,"mn":"ADBE Vector Group","hd":false}],"ip":0,"op":60.9999945377493,"st":0,"bm":0},{"ddd":0,"ind":16,"ty":4,"nm":"arm2line1","parent":37,"sr":1,"ks":{"o":{"a":0,"k":100,"ix":11},"r":{"a":1,"k":[{"i":{"x":[0.667],"y":[1]},"o":{"x":[0.333],"y":[0]},"n":["0p667_1_0p333_0"],"t":0,"s":[0],"e":[-30]},{"i":{"x":[0.667],"y":[1]},"o":{"x":[0.333],"y":[0]},"n":["0p667_1_0p333_0"],"t":18,"s":[-30],"e":[-4]},{"i":{"x":[0.667],"y":[1]},"o":{"x":[0.333],"y":[0]},"n":["0p667_1_0p333_0"],"t":38,"s":[-4],"e":[-22]},{"i":{"x":[0.667],"y":[1]},"o":{"x":[0.333],"y":[0]},"n":["0p667_1_0p333_0"],"t":49,"s":[-22],"e":[0]},{"t":59.9999946272944}],"ix":10},"p":{"a":0,"k":[-47.5,-20.5,0],"ix":2},"a":{"a":0,"k":[-47.5,-20.5,0],"ix":1},"s":{"a":0,"k":[100,100,100],"ix":6}},"ao":0,"shapes":[{"ty":"gr","it":[{"ind":0,"ty":"sh","ix":1,"ks":{"a":0,"k":{"i":[[0,0],[62,3],[0,0]],"o":[[0,0],[-62,-3],[0,0]],"v":[[-47.5,-20.5],[-161.5,-91.5],[-203.5,-24.5]],"c":false},"ix":2},"nm":"Path 1","mn":"ADBE Vector Shape - Group","hd":false},{"ty":"st","c":{"a":0,"k":[0.23137254902,0.149019607843,0.349019607843,1],"ix":3},"o":{"a":0,"k":100,"ix":4},"w":{"a":0,"k":4,"ix":5},"lc":1,"lj":1,"ml":10,"ml2":{"a":0,"k":10,"ix":8},"nm":"Stroke 1","mn":"ADBE Vector Graphic - Stroke","hd":false},{"ty":"tr","p":{"a":0,"k":[0,0],"ix":2},"a":{"a":0,"k":[0,0],"ix":1},"s":{"a":0,"k":[100,100],"ix":3},"r":{"a":0,"k":0,"ix":6},"o":{"a":0,"k":100,"ix":7},"sk":{"a":0,"k":0,"ix":4},"sa":{"a":0,"k":0,"ix":5},"nm":"Transform"}],"nm":"Group 1","np":2,"cix":2,"ix":1,"mn":"ADBE Vector Group","hd":false}],"ip":0,"op":60.9999945377493,"st":0,"bm":0},{"ddd":0,"ind":19,"ty":4,"nm":"hand1","parent":20,"sr":1,"ks":{"o":{"a":0,"k":100,"ix":11},"r":{"a":0,"k":0,"ix":10},"p":{"a":0,"k":[142.006,-294.78,0],"ix":2},"a":{"a":0,"k":[142.006,-294.78,0],"ix":1},"s":{"a":0,"k":[100,100,100],"ix":6}},"ao":0,"shapes":[{"ty":"gr","it":[{"ind":0,"ty":"sh","ix":1,"ks":{"a":0,"k":{"i":[[0,0],[0,0],[17,2],[0,0],[-3,-6],[34,-14],[0,0],[-32,-20],[13.959,-11.965],[0,0],[-17,0]],"o":[[0,0],[0,0],[-17,-2],[0,0],[0,0],[-30.779,12.674],[0,0],[0,0],[-14,12],[0,0],[12.649,0]],"v":[[199.5,-272.5],[207.5,-287.5],[191.5,-325.5],[163.5,-323.5],[190.5,-309.5],[121.5,-307.5],[76.5,-278.5],[181.5,-291.5],[154.5,-286.5],[143.5,-263.5],[170.5,-275.5]],"c":true},"ix":2},"nm":"Path 1","mn":"ADBE Vector Shape - Group","hd":false},{"ty":"fl","c":{"a":0,"k":[0.23137254902,0.149019607843,0.349019607843,1],"ix":4},"o":{"a":0,"k":100,"ix":5},"r":1,"nm":"Fill 1","mn":"ADBE Vector Graphic - Fill","hd":false},{"ty":"tr","p":{"a":0,"k":[0,0],"ix":2},"a":{"a":0,"k":[0,0],"ix":1},"s":{"a":0,"k":[100,100],"ix":3},"r":{"a":0,"k":0,"ix":6},"o":{"a":0,"k":100,"ix":7},"sk":{"a":0,"k":0,"ix":4},"sa":{"a":0,"k":0,"ix":5},"nm":"Transform"}],"nm":"Group 1","np":2,"cix":2,"ix":1,"mn":"ADBE Vector Group","hd":false}],"ip":0,"op":60.9999945377493,"st":0,"bm":0},{"ddd":0,"ind":20,"ty":4,"nm":"arm1line2","parent":21,"sr":1,"ks":{"o":{"a":0,"k":100,"ix":11},"r":{"a":0,"k":0,"ix":10},"p":{"a":0,"k":[250,-148.5,0],"ix":2},"a":{"a":0,"k":[250,-148.5,0],"ix":1},"s":{"a":0,"k":[100,100,100],"ix":6}},"ao":0,"shapes":[{"ty":"gr","it":[{"ind":0,"ty":"sh","ix":1,"ks":{"a":0,"k":{"i":[[0,0],[0,-115],[0,0]],"o":[[0,0],[0,115],[0,0]],"v":[[204.5,-287.5],[303.5,-148.5],[196.5,-9.5]],"c":false},"ix":2},"nm":"Path 1","mn":"ADBE Vector Shape - Group","hd":false},{"ty":"st","c":{"a":0,"k":[0.23137254902,0.149019607843,0.349019607843,1],"ix":3},"o":{"a":0,"k":100,"ix":4},"w":{"a":0,"k":4,"ix":5},"lc":1,"lj":1,"ml":10,"ml2":{"a":0,"k":10,"ix":8},"nm":"Stroke 1","mn":"ADBE Vector Graphic - Stroke","hd":false},{"ty":"tr","p":{"a":0,"k":[0,0],"ix":2},"a":{"a":0,"k":[0,0],"ix":1},"s":{"a":0,"k":[100,100],"ix":3},"r":{"a":0,"k":0,"ix":6},"o":{"a":0,"k":100,"ix":7},"sk":{"a":0,"k":0,"ix":4},"sa":{"a":0,"k":0,"ix":5},"nm":"Transform"}],"nm":"Group 1","np":2,"cix":2,"ix":1,"mn":"ADBE Vector Group","hd":false}],"ip":0,"op":60.9999945377493,"st":0,"bm":0},{"ddd":0,"ind":21,"ty":4,"nm":"arm1line1","parent":37,"sr":1,"ks":{"o":{"a":0,"k":100,"ix":11},"r":{"a":1,"k":[{"i":{"x":[0.667],"y":[1]},"o":{"x":[0.333],"y":[0]},"n":["0p667_1_0p333_0"],"t":0,"s":[11],"e":[3]},{"i":{"x":[0.667],"y":[1]},"o":{"x":[0.333],"y":[0]},"n":["0p667_1_0p333_0"],"t":17,"s":[3],"e":[7]},{"i":{"x":[0.667],"y":[1]},"o":{"x":[0.333],"y":[0]},"n":["0p667_1_0p333_0"],"t":36,"s":[7],"e":[-4]},{"i":{"x":[0.667],"y":[1]},"o":{"x":[0.333],"y":[0]},"n":["0p667_1_0p333_0"],"t":49,"s":[-4],"e":[11]},{"t":59.9999946272944}],"ix":10},"p":{"a":0,"k":[163.5,-77.5,0],"ix":2},"a":{"a":0,"k":[163.5,-77.5,0],"ix":1},"s":{"a":0,"k":[100,100,100],"ix":6}},"ao":0,"shapes":[{"ty":"gr","it":[{"ind":0,"ty":"sh","ix":1,"ks":{"a":0,"k":{"i":[[0,0],[2,82],[0,0]],"o":[[0,0],[-1.804,-73.958],[0,0]],"v":[[163.5,-77.5],[253.5,-187.5],[197.5,-278.5]],"c":false},"ix":2},"nm":"Path 1","mn":"ADBE Vector Shape - Group","hd":false},{"ty":"st","c":{"a":0,"k":[0.23137254902,0.149019607843,0.349019607843,1],"ix":3},"o":{"a":0,"k":100,"ix":4},"w":{"a":0,"k":4,"ix":5},"lc":1,"lj":1,"ml":10,"ml2":{"a":0,"k":10,"ix":8},"nm":"Stroke 1","mn":"ADBE Vector Graphic - Stroke","hd":false},{"ty":"tr","p":{"a":0,"k":[0,0],"ix":2},"a":{"a":0,"k":[0,0],"ix":1},"s":{"a":0,"k":[100,100],"ix":3},"r":{"a":0,"k":0,"ix":6},"o":{"a":0,"k":100,"ix":7},"sk":{"a":0,"k":0,"ix":4},"sa":{"a":0,"k":0,"ix":5},"nm":"Transform"}],"nm":"Group 1","np":2,"cix":2,"ix":1,"mn":"ADBE Vector Group","hd":false}],"ip":0,"op":60.9999945377493,"st":0,"bm":0},{"ddd":0,"ind":22,"ty":4,"nm":"pupil2","parent":23,"sr":1,"ks":{"o":{"a":0,"k":100,"ix":11},"r":{"a":0,"k":0,"ix":10},"p":{"s":true,"x":{"a":0,"k":0,"ix":3},"y":{"a":1,"k":[{"i":{"x":[0.833],"y":[1]},"o":{"x":[0.333],"y":[0]},"n":["0p833_1_0p333_0"],"t":0,"s":[-3.625],"e":[9.375]},{"i":{"x":[0.833],"y":[1]},"o":{"x":[0.167],"y":[0]},"n":["0p833_1_0p167_0"],"t":21,"s":[9.375],"e":[-3.625]},{"i":{"x":[0.667],"y":[1]},"o":{"x":[0.167],"y":[0]},"n":["0p667_1_0p167_0"],"t":42,"s":[-3.625],"e":[-3.625]},{"t":59.9999946272944}],"ix":4}},"a":{"a":0,"k":[-8,-169,0],"ix":1},"s":{"a":0,"k":[100,100,100],"ix":6}},"ao":0,"shapes":[{"ty":"gr","it":[{"ind":0,"ty":"sh","ix":1,"ks":{"a":0,"k":{"i":[[-8.006,-8.006],[8.006,-8.006],[8.006,8.006],[-8.006,8.006]],"o":[[8.006,8.006],[-8.006,8.006],[-8.006,-8.006],[8.006,-8.006]],"v":[[6.496,-183.496],[6.496,-154.504],[-22.496,-154.504],[-22.496,-183.496]],"c":true},"ix":2},"nm":"Path 1","mn":"ADBE Vector Shape - Group","hd":false},{"ty":"fl","c":{"a":0,"k":[0.231372563979,0.149019607843,0.349019607843,1],"ix":4},"o":{"a":0,"k":100,"ix":5},"r":1,"nm":"Fill 1","mn":"ADBE Vector Graphic - Fill","hd":false},{"ty":"tr","p":{"a":0,"k":[0,0],"ix":2},"a":{"a":0,"k":[0,0],"ix":1},"s":{"a":0,"k":[100,100],"ix":3},"r":{"a":0,"k":0,"ix":6},"o":{"a":0,"k":100,"ix":7},"sk":{"a":0,"k":0,"ix":4},"sa":{"a":0,"k":0,"ix":5},"nm":"Transform"}],"nm":"Group 1","np":2,"cix":2,"ix":1,"mn":"ADBE Vector Group","hd":false}],"ip":0,"op":60.9999945377493,"st":0,"bm":0},{"ddd":0,"ind":23,"ty":4,"nm":"eye2","parent":37,"sr":1,"ks":{"o":{"a":0,"k":100,"ix":11},"r":{"a":0,"k":0,"ix":10},"p":{"s":true,"x":{"a":0,"k":23.553,"ix":3},"y":{"a":1,"k":[{"i":{"x":[0.833],"y":[1]},"o":{"x":[0.333],"y":[0]},"n":["0p833_1_0p333_0"],"t":-1,"s":[-198.113],"e":[-171.113]},{"i":{"x":[0.833],"y":[1]},"o":{"x":[0.167],"y":[0]},"n":["0p833_1_0p167_0"],"t":5,"s":[-171.113],"e":[-200.113]},{"i":{"x":[0.833],"y":[1]},"o":{"x":[0.167],"y":[0]},"n":["0p833_1_0p167_0"],"t":19,"s":[-200.113],"e":[-179.113]},{"i":{"x":[0.833],"y":[1]},"o":{"x":[0.167],"y":[0]},"n":["0p833_1_0p167_0"],"t":33,"s":[-179.113],"e":[-200.113]},{"i":{"x":[0.667],"y":[1]},"o":{"x":[0.167],"y":[0]},"n":["0p667_1_0p167_0"],"t":48,"s":[-200.113],"e":[-198.113]},{"t":59.9999946272944}],"ix":4}},"a":{"a":0,"k":[0,0,0],"ix":1},"s":{"a":0,"k":[153.303,156.6,100],"ix":6}},"ao":0,"shapes":[{"ty":"gr","it":[{"d":1,"ty":"el","s":{"a":0,"k":[51,51],"ix":2},"p":{"a":0,"k":[0,0],"ix":3},"nm":"Ellipse Path 1","mn":"ADBE Vector Shape - Ellipse","hd":false},{"ty":"st","c":{"a":0,"k":[0.231372563979,0.149019607843,0.349019607843,1],"ix":3},"o":{"a":0,"k":100,"ix":4},"w":{"a":0,"k":4,"ix":5},"lc":1,"lj":1,"ml":10,"ml2":{"a":0,"k":10,"ix":8},"nm":"Stroke 1","mn":"ADBE Vector Graphic - Stroke","hd":false},{"ty":"fl","c":{"a":0,"k":[1,1,1,1],"ix":4},"o":{"a":0,"k":100,"ix":5},"r":1,"nm":"Fill 1","mn":"ADBE Vector Graphic - Fill","hd":false},{"ty":"tr","p":{"a":0,"k":[0,0],"ix":2},"a":{"a":0,"k":[0,0],"ix":1},"s":{"a":0,"k":[100,100],"ix":3},"r":{"a":0,"k":0,"ix":6},"o":{"a":0,"k":100,"ix":7},"sk":{"a":0,"k":0,"ix":4},"sa":{"a":0,"k":0,"ix":5},"nm":"Transform"}],"nm":"Group 1","np":3,"cix":2,"ix":1,"mn":"ADBE Vector Group","hd":false}],"ip":0,"op":60.9999945377493,"st":0,"bm":0},{"ddd":0,"ind":24,"ty":4,"nm":"pupil1","parent":25,"sr":1,"ks":{"o":{"a":0,"k":100,"ix":11},"r":{"a":0,"k":0,"ix":10},"p":{"s":true,"x":{"a":0,"k":0,"ix":3},"y":{"a":1,"k":[{"i":{"x":[0.833],"y":[1]},"o":{"x":[0.333],"y":[0]},"n":["0p833_1_0p333_0"],"t":0,"s":[-4.375],"e":[8.625]},{"i":{"x":[0.833],"y":[1]},"o":{"x":[0.167],"y":[0]},"n":["0p833_1_0p167_0"],"t":21,"s":[8.625],"e":[-4.375]},{"i":{"x":[0.667],"y":[1]},"o":{"x":[0.167],"y":[0]},"n":["0p667_1_0p167_0"],"t":42,"s":[-4.375],"e":[-4.375]},{"t":59.9999946272944}],"ix":4}},"a":{"a":0,"k":[0,0,0],"ix":1},"s":{"a":0,"k":[100,100,100],"ix":6}},"ao":0,"shapes":[{"ty":"gr","it":[{"d":1,"ty":"el","s":{"a":0,"k":[41,41],"ix":2},"p":{"a":0,"k":[0,0],"ix":3},"nm":"Ellipse Path 1","mn":"ADBE Vector Shape - Ellipse","hd":false},{"ty":"fl","c":{"a":0,"k":[0.231372563979,0.149019607843,0.349019607843,1],"ix":4},"o":{"a":0,"k":100,"ix":5},"r":1,"nm":"Fill 1","mn":"ADBE Vector Graphic - Fill","hd":false},{"ty":"tr","p":{"a":0,"k":[0,0],"ix":2},"a":{"a":0,"k":[0,0],"ix":1},"s":{"a":0,"k":[100,100],"ix":3},"r":{"a":0,"k":0,"ix":6},"o":{"a":0,"k":100,"ix":7},"sk":{"a":0,"k":0,"ix":4},"sa":{"a":0,"k":0,"ix":5},"nm":"Transform"}],"nm":"Group 1","np":2,"cix":2,"ix":1,"mn":"ADBE Vector Group","hd":false}],"ip":0,"op":60.9999945377493,"st":0,"bm":0},{"ddd":0,"ind":25,"ty":4,"nm":"eye1","parent":37,"sr":1,"ks":{"o":{"a":0,"k":100,"ix":11},"r":{"a":0,"k":0,"ix":10},"p":{"s":true,"x":{"a":0,"k":122.35,"ix":3},"y":{"a":1,"k":[{"i":{"x":[0.833],"y":[1]},"o":{"x":[0.333],"y":[0]},"n":["0p833_1_0p333_0"],"t":-1,"s":[-199.309],"e":[-172.309]},{"i":{"x":[0.833],"y":[1]},"o":{"x":[0.167],"y":[0]},"n":["0p833_1_0p167_0"],"t":5,"s":[-172.309],"e":[-201.309]},{"i":{"x":[0.833],"y":[1]},"o":{"x":[0.167],"y":[0]},"n":["0p833_1_0p167_0"],"t":19,"s":[-201.309],"e":[-180.309]},{"i":{"x":[0.833],"y":[1]},"o":{"x":[0.167],"y":[0]},"n":["0p833_1_0p167_0"],"t":33,"s":[-180.309],"e":[-201.309]},{"i":{"x":[0.667],"y":[1]},"o":{"x":[0.167],"y":[0]},"n":["0p667_1_0p167_0"],"t":48,"s":[-201.309],"e":[-199.309]},{"t":59.9999946272944}],"ix":4}},"a":{"a":0,"k":[0,0,0],"ix":1},"s":{"a":0,"k":[134.266,140.429,100],"ix":6}},"ao":0,"shapes":[{"ty":"gr","it":[{"d":1,"ty":"el","s":{"a":0,"k":[51,51],"ix":2},"p":{"a":0,"k":[0,0],"ix":3},"nm":"Ellipse Path 1","mn":"ADBE Vector Shape - Ellipse","hd":false},{"ty":"st","c":{"a":0,"k":[0.231372563979,0.149019607843,0.349019607843,1],"ix":3},"o":{"a":0,"k":100,"ix":4},"w":{"a":0,"k":4,"ix":5},"lc":1,"lj":1,"ml":10,"ml2":{"a":0,"k":10,"ix":8},"nm":"Stroke 1","mn":"ADBE Vector Graphic - Stroke","hd":false},{"ty":"fl","c":{"a":0,"k":[1,1,1,1],"ix":4},"o":{"a":0,"k":100,"ix":5},"r":1,"nm":"Fill 1","mn":"ADBE Vector Graphic - Fill","hd":false},{"ty":"tr","p":{"a":0,"k":[0,0],"ix":2},"a":{"a":0,"k":[0,0],"ix":1},"s":{"a":0,"k":[100,100],"ix":3},"r":{"a":0,"k":0,"ix":6},"o":{"a":0,"k":100,"ix":7},"sk":{"a":0,"k":0,"ix":4},"sa":{"a":0,"k":0,"ix":5},"nm":"Transform"}],"nm":"Group 1","np":3,"cix":2,"ix":1,"mn":"ADBE Vector Group","hd":false}],"ip":0,"op":60.9999945377493,"st":0,"bm":0},{"ddd":0,"ind":26,"ty":4,"nm":"tooth2","parent":28,"sr":1,"ks":{"o":{"a":0,"k":100,"ix":11},"r":{"a":0,"k":0,"ix":10},"p":{"a":0,"k":[71.547,-129.183,0],"ix":2},"a":{"a":0,"k":[71.547,-129.183,0],"ix":1},"s":{"a":0,"k":[100,100,100],"ix":6}},"ao":0,"shapes":[{"ty":"gr","it":[{"ind":0,"ty":"sh","ix":1,"ks":{"a":0,"k":{"i":[[0,0],[0,0],[0,0],[0,0]],"o":[[0,0],[0,0],[0,0],[0,0]],"v":[[65.593,-131.665],[74.185,-116.551],[80.949,-119.277],[76.889,-147.412]],"c":true},"ix":2},"nm":"Path 1","mn":"ADBE Vector Shape - Group","hd":false},{"ty":"fl","c":{"a":0,"k":[1,1,1,1],"ix":4},"o":{"a":0,"k":100,"ix":5},"r":1,"nm":"Fill 1","mn":"ADBE Vector Graphic - Fill","hd":false},{"ty":"tr","p":{"a":0,"k":[0,0],"ix":2},"a":{"a":0,"k":[0,0],"ix":1},"s":{"a":0,"k":[100,100],"ix":3},"r":{"a":0,"k":0,"ix":6},"o":{"a":0,"k":100,"ix":7},"sk":{"a":0,"k":0,"ix":4},"sa":{"a":0,"k":0,"ix":5},"nm":"Transform"}],"nm":"Group 1","np":2,"cix":2,"ix":1,"mn":"ADBE Vector Group","hd":false}],"ip":0,"op":60.9999945377493,"st":0,"bm":0},{"ddd":0,"ind":27,"ty":4,"nm":"tooth1","parent":28,"sr":1,"ks":{"o":{"a":0,"k":100,"ix":11},"r":{"a":0,"k":0,"ix":10},"p":{"a":0,"k":[61.119,-123.711,0],"ix":2},"a":{"a":0,"k":[61.119,-123.711,0],"ix":1},"s":{"a":0,"k":[100,100,100],"ix":6}},"ao":0,"shapes":[{"ty":"gr","it":[{"ind":0,"ty":"sh","ix":1,"ks":{"a":0,"k":{"i":[[0,0],[0,0],[0,0],[0,0]],"o":[[0,0],[0,0],[0,0],[0,0]],"v":[[43.121,-131.402],[66.145,-112.522],[73.01,-114.865],[63.5,-130.922]],"c":true},"ix":2},"nm":"Path 1","mn":"ADBE Vector Shape - Group","hd":false},{"ty":"fl","c":{"a":0,"k":[1,1,1,1],"ix":4},"o":{"a":0,"k":100,"ix":5},"r":1,"nm":"Fill 1","mn":"ADBE Vector Graphic - Fill","hd":false},{"ty":"tr","p":{"a":0,"k":[0,0],"ix":2},"a":{"a":0,"k":[0,0],"ix":1},"s":{"a":0,"k":[100,100],"ix":3},"r":{"a":0,"k":0,"ix":6},"o":{"a":0,"k":100,"ix":7},"sk":{"a":0,"k":0,"ix":4},"sa":{"a":0,"k":0,"ix":5},"nm":"Transform"}],"nm":"Group 1","np":2,"cix":2,"ix":1,"mn":"ADBE Vector Group","hd":false}],"ip":0,"op":60.9999945377493,"st":0,"bm":0},{"ddd":0,"ind":28,"ty":4,"nm":"mouth1","parent":37,"sr":1,"ks":{"o":{"a":0,"k":100,"ix":11},"r":{"a":0,"k":29,"ix":10},"p":{"a":0,"k":[80.843,-121.755,0],"ix":2},"a":{"a":0,"k":[66.28,-119.693,0],"ix":1},"s":{"a":0,"k":[100,100,100],"ix":6}},"ao":0,"shapes":[{"ty":"gr","it":[{"ind":0,"ty":"sh","ix":1,"ks":{"a":1,"k":[{"i":{"x":0.667,"y":1},"o":{"x":0.333,"y":0},"n":"0p667_1_0p333_0","t":1,"s":[{"i":[[0,0],[-12.131,12.052],[-11.4,5.57],[-14.297,6.953],[-3.168,-16.812],[14.189,-5.301]],"o":[[0,0],[9.111,-9.052],[16.032,-7.834],[0,0],[2.219,11.778],[-24.895,9.302]],"v":[[37.183,-107.257],[31.257,-131.806],[61.413,-131.871],[82.573,-152.184],[99.284,-137.119],[80.321,-102.618]],"c":true}],"e":[{"i":[[0,0],[-13.304,10.743],[-11.4,5.57],[-14.297,6.953],[-3.168,-16.812],[14.189,-5.301]],"o":[[0,0],[8.501,-6.865],[16.032,-7.834],[0,0],[2.219,11.778],[-24.895,9.302]],"v":[[49.607,-94.822],[34.435,-130.042],[62.393,-132.332],[83.125,-149.887],[98.911,-126.523],[89.055,-83.972]],"c":true}]},{"i":{"x":0.667,"y":1},"o":{"x":0.333,"y":0},"n":"0p667_1_0p333_0","t":16,"s":[{"i":[[0,0],[-13.304,10.743],[-11.4,5.57],[-14.297,6.953],[-3.168,-16.812],[14.189,-5.301]],"o":[[0,0],[8.501,-6.865],[16.032,-7.834],[0,0],[2.219,11.778],[-24.895,9.302]],"v":[[49.607,-94.822],[34.435,-130.042],[62.393,-132.332],[83.125,-149.887],[98.911,-126.523],[89.055,-83.972]],"c":true}],"e":[{"i":[[0,0],[-12.131,12.052],[-11.4,5.57],[-14.297,6.953],[-3.168,-16.812],[21.6,-9.65]],"o":[[0,0],[9.111,-9.052],[16.032,-7.834],[0,0],[2.219,11.778],[-27.043,12.082]],"v":[[32.2,-104.581],[27.247,-125.563],[61.413,-131.871],[88.433,-156.272],[104.997,-139.046],[76.831,-103.203]],"c":true}]},{"i":{"x":0.667,"y":1},"o":{"x":0.333,"y":0},"n":"0p667_1_0p333_0","t":33,"s":[{"i":[[0,0],[-12.131,12.052],[-11.4,5.57],[-14.297,6.953],[-3.168,-16.812],[21.6,-9.65]],"o":[[0,0],[9.111,-9.052],[16.032,-7.834],[0,0],[2.219,11.778],[-27.043,12.082]],"v":[[32.2,-104.581],[27.247,-125.563],[61.413,-131.871],[88.433,-156.272],[104.997,-139.046],[76.831,-103.203]],"c":true}],"e":[{"i":[[0,0],[-13.304,10.743],[-11.4,5.57],[-14.297,6.953],[-3.168,-16.812],[14.189,-5.301]],"o":[[0,0],[8.501,-6.865],[16.032,-7.834],[0,0],[2.219,11.778],[-24.895,9.302]],"v":[[49.607,-94.822],[34.435,-130.042],[62.393,-132.332],[83.125,-149.887],[98.911,-126.523],[89.055,-83.972]],"c":true}]},{"i":{"x":0.667,"y":1},"o":{"x":0.333,"y":0},"n":"0p667_1_0p333_0","t":47,"s":[{"i":[[0,0],[-13.304,10.743],[-11.4,5.57],[-14.297,6.953],[-3.168,-16.812],[14.189,-5.301]],"o":[[0,0],[8.501,-6.865],[16.032,-7.834],[0,0],[2.219,11.778],[-24.895,9.302]],"v":[[49.607,-94.822],[34.435,-130.042],[62.393,-132.332],[83.125,-149.887],[98.911,-126.523],[89.055,-83.972]],"c":true}],"e":[{"i":[[0,0],[-12.131,12.052],[-11.4,5.57],[-14.297,6.953],[-3.168,-16.812],[14.189,-5.301]],"o":[[0,0],[9.111,-9.052],[16.032,-7.834],[0,0],[2.219,11.778],[-24.895,9.302]],"v":[[37.183,-107.257],[31.257,-131.806],[61.413,-131.871],[82.573,-152.184],[99.284,-137.119],[80.321,-102.618]],"c":true}]},{"t":59.9999946272944}],"ix":2},"nm":"Path 1","mn":"ADBE Vector Shape - Group","hd":false},{"ty":"fl","c":{"a":0,"k":[0.231372563979,0.149019607843,0.349019607843,1],"ix":4},"o":{"a":0,"k":100,"ix":5},"r":1,"nm":"Fill 1","mn":"ADBE Vector Graphic - Fill","hd":false},{"ty":"tr","p":{"a":0,"k":[0,0],"ix":2},"a":{"a":0,"k":[0,0],"ix":1},"s":{"a":0,"k":[100,100],"ix":3},"r":{"a":0,"k":0,"ix":6},"o":{"a":0,"k":100,"ix":7},"sk":{"a":0,"k":0,"ix":4},"sa":{"a":0,"k":0,"ix":5},"nm":"Transform"}],"nm":"Group 1","np":2,"cix":2,"ix":1,"mn":"ADBE Vector Group","hd":false}],"ip":0,"op":60.9999945377493,"st":0,"bm":0},{"ddd":0,"ind":29,"ty":4,"nm":"crownEffect2","parent":31,"sr":1,"ks":{"o":{"a":0,"k":100,"ix":11},"r":{"a":0,"k":0,"ix":10},"p":{"a":0,"k":[-121.5,-339.5,0],"ix":2},"a":{"a":0,"k":[-121.5,-339.5,0],"ix":1},"s":{"a":0,"k":[100,100,100],"ix":6}},"ao":0,"shapes":[{"ty":"gr","it":[{"ind":0,"ty":"sh","ix":1,"ks":{"a":0,"k":{"i":[[0,0],[0,0],[0,0]],"o":[[0,0],[0,0],[0,0]],"v":[[-127.5,-326.5],[-115.5,-352.5],[-118.5,-326.5]],"c":true},"ix":2},"nm":"Path 1","mn":"ADBE Vector Shape - Group","hd":false},{"ty":"fl","c":{"a":0,"k":[0.392156862745,0.156862745098,0.56862745098,1],"ix":4},"o":{"a":0,"k":100,"ix":5},"r":1,"nm":"Fill 1","mn":"ADBE Vector Graphic - Fill","hd":false},{"ty":"tr","p":{"a":0,"k":[0,0],"ix":2},"a":{"a":0,"k":[0,0],"ix":1},"s":{"a":0,"k":[100,100],"ix":3},"r":{"a":0,"k":0,"ix":6},"o":{"a":0,"k":100,"ix":7},"sk":{"a":0,"k":0,"ix":4},"sa":{"a":0,"k":0,"ix":5},"nm":"Transform"}],"nm":"Group 1","np":2,"cix":2,"ix":1,"mn":"ADBE Vector Group","hd":false}],"ip":0,"op":60.9999945377493,"st":0,"bm":0},{"ddd":0,"ind":30,"ty":4,"nm":"crownEffect1","parent":31,"sr":1,"ks":{"o":{"a":0,"k":100,"ix":11},"r":{"a":0,"k":0,"ix":10},"p":{"a":0,"k":[-254,-283,0],"ix":2},"a":{"a":0,"k":[-254,-283,0],"ix":1},"s":{"a":0,"k":[100,100,100],"ix":6}},"ao":0,"shapes":[{"ty":"gr","it":[{"ind":0,"ty":"sh","ix":1,"ks":{"a":0,"k":{"i":[[0,0],[0,0],[0,0]],"o":[[0,0],[0,0],[0,0]],"v":[[-243.5,-287.5],[-264.5,-287.5],[-243.5,-278.5]],"c":true},"ix":2},"nm":"Path 1","mn":"ADBE Vector Shape - Group","hd":false},{"ty":"fl","c":{"a":0,"k":[0.392156862745,0.156862745098,0.56862745098,1],"ix":4},"o":{"a":0,"k":100,"ix":5},"r":1,"nm":"Fill 1","mn":"ADBE Vector Graphic - Fill","hd":false},{"ty":"tr","p":{"a":0,"k":[0,0],"ix":2},"a":{"a":0,"k":[0,0],"ix":1},"s":{"a":0,"k":[100,100],"ix":3},"r":{"a":0,"k":0,"ix":6},"o":{"a":0,"k":100,"ix":7},"sk":{"a":0,"k":0,"ix":4},"sa":{"a":0,"k":0,"ix":5},"nm":"Transform"}],"nm":"Group 1","np":2,"cix":2,"ix":1,"mn":"ADBE Vector Group","hd":false}],"ip":0,"op":60.9999945377493,"st":0,"bm":0},{"ddd":0,"ind":31,"ty":4,"nm":"crown","parent":37,"sr":1,"ks":{"o":{"a":0,"k":100,"ix":11},"r":{"a":1,"k":[{"i":{"x":[0.667],"y":[1]},"o":{"x":[0.333],"y":[0]},"n":["0p667_1_0p333_0"],"t":-1,"s":[0],"e":[-44]},{"i":{"x":[0.667],"y":[1]},"o":{"x":[0.333],"y":[0]},"n":["0p667_1_0p333_0"],"t":16,"s":[-44],"e":[20]},{"i":{"x":[0.667],"y":[1]},"o":{"x":[0.333],"y":[0]},"n":["0p667_1_0p333_0"],"t":32,"s":[20],"e":[-46]},{"i":{"x":[0.667],"y":[1]},"o":{"x":[0.333],"y":[0]},"n":["0p667_1_0p333_0"],"t":45,"s":[-46],"e":[0]},{"t":59.9999946272944}],"ix":10},"p":{"a":0,"k":[-151.665,-260.75,0],"ix":2},"a":{"a":0,"k":[-151.665,-260.75,0],"ix":1},"s":{"a":0,"k":[100,100,100],"ix":6}},"ao":0,"shapes":[{"ty":"gr","it":[{"ind":0,"ty":"sh","ix":1,"ks":{"a":0,"k":{"i":[[0,0],[4,7],[0,0],[0,0],[0,0],[0,0],[0,0]],"o":[[0,0],[-4,-7],[0,0],[0,0],[0,0],[0,0],[0,0]],"v":[[-185.5,-248.5],[-121.5,-287.5],[-153.5,-345.5],[-166.5,-310.5],[-207.5,-352.5],[-195.5,-278.5],[-218.5,-278.5]],"c":true},"ix":2},"nm":"Path 1","mn":"ADBE Vector Shape - Group","hd":false},{"ty":"fl","c":{"a":0,"k":[0.392156862745,0.156862745098,0.56862745098,1],"ix":4},"o":{"a":0,"k":100,"ix":5},"r":1,"nm":"Fill 1","mn":"ADBE Vector Graphic - Fill","hd":false},{"ty":"tr","p":{"a":0,"k":[0,0],"ix":2},"a":{"a":0,"k":[0,0],"ix":1},"s":{"a":0,"k":[100,100],"ix":3},"r":{"a":0,"k":0,"ix":6},"o":{"a":0,"k":100,"ix":7},"sk":{"a":0,"k":0,"ix":4},"sa":{"a":0,"k":0,"ix":5},"nm":"Transform"}],"nm":"Group 1","np":2,"cix":2,"ix":1,"mn":"ADBE Vector Group","hd":false}],"ip":0,"op":60.9999945377493,"st":0,"bm":0},{"ddd":0,"ind":32,"ty":4,"nm":"hair2","parent":37,"sr":1,"ks":{"o":{"a":0,"k":100,"ix":11},"r":{"a":1,"k":[{"i":{"x":[0.667],"y":[1]},"o":{"x":[0.333],"y":[0]},"n":["0p667_1_0p333_0"],"t":0,"s":[0],"e":[7]},{"i":{"x":[0.667],"y":[1]},"o":{"x":[0.333],"y":[0]},"n":["0p667_1_0p333_0"],"t":17,"s":[7],"e":[-8]},{"i":{"x":[0.667],"y":[1]},"o":{"x":[0.333],"y":[0]},"n":["0p667_1_0p333_0"],"t":34,"s":[-8],"e":[2]},{"i":{"x":[0.667],"y":[1]},"o":{"x":[0.333],"y":[0]},"n":["0p667_1_0p333_0"],"t":46,"s":[2],"e":[0]},{"t":59.9999946272944}],"ix":10},"p":{"a":0,"k":[142.5,-10.5,0],"ix":2},"a":{"a":0,"k":[142.5,-10.5,0],"ix":1},"s":{"a":0,"k":[100,100,100],"ix":6}},"ao":0,"shapes":[{"ty":"gr","it":[{"ind":0,"ty":"sh","ix":1,"ks":{"a":0,"k":{"i":[[0,0],[-14,-4]],"o":[[0,0],[0,0]],"v":[[142.5,-10.5],[167.5,0.5]],"c":false},"ix":2},"nm":"Path 1","mn":"ADBE Vector Shape - Group","hd":false},{"ty":"st","c":{"a":0,"k":[0.392156892664,0.156862745098,0.56862745098,1],"ix":3},"o":{"a":0,"k":100,"ix":4},"w":{"a":0,"k":4,"ix":5},"lc":1,"lj":1,"ml":10,"ml2":{"a":0,"k":10,"ix":8},"nm":"Stroke 1","mn":"ADBE Vector Graphic - Stroke","hd":false},{"ty":"tr","p":{"a":0,"k":[0,0],"ix":2},"a":{"a":0,"k":[0,0],"ix":1},"s":{"a":0,"k":[100,100],"ix":3},"r":{"a":0,"k":0,"ix":6},"o":{"a":0,"k":100,"ix":7},"sk":{"a":0,"k":0,"ix":4},"sa":{"a":0,"k":0,"ix":5},"nm":"Transform"}],"nm":"Group 1","np":2,"cix":2,"ix":1,"mn":"ADBE Vector Group","hd":false}],"ip":0,"op":60.9999945377493,"st":0,"bm":0},{"ddd":0,"ind":33,"ty":4,"nm":"hair1","parent":37,"sr":1,"ks":{"o":{"a":0,"k":100,"ix":11},"r":{"a":1,"k":[{"i":{"x":[0.667],"y":[1]},"o":{"x":[0.333],"y":[0]},"n":["0p667_1_0p333_0"],"t":0,"s":[0],"e":[8]},{"i":{"x":[0.667],"y":[1]},"o":{"x":[0.333],"y":[0]},"n":["0p667_1_0p333_0"],"t":17,"s":[8],"e":[-3]},{"i":{"x":[0.667],"y":[1]},"o":{"x":[0.333],"y":[0]},"n":["0p667_1_0p333_0"],"t":34,"s":[-3],"e":[5]},{"i":{"x":[0.667],"y":[1]},"o":{"x":[0.333],"y":[0]},"n":["0p667_1_0p333_0"],"t":46,"s":[5],"e":[0]},{"t":59.9999946272944}],"ix":10},"p":{"a":0,"k":[129.5,-41.5,0],"ix":2},"a":{"a":0,"k":[129.5,-41.5,0],"ix":1},"s":{"a":0,"k":[100,100,100],"ix":6}},"ao":0,"shapes":[{"ty":"gr","it":[{"ind":0,"ty":"sh","ix":1,"ks":{"a":0,"k":{"i":[[0,0],[-38,10]],"o":[[0,0],[0,0]],"v":[[129.5,-41.5],[187.5,-37.5]],"c":false},"ix":2},"nm":"Path 1","mn":"ADBE Vector Shape - Group","hd":false},{"ty":"st","c":{"a":0,"k":[0.392156892664,0.156862745098,0.56862745098,1],"ix":3},"o":{"a":0,"k":100,"ix":4},"w":{"a":0,"k":4,"ix":5},"lc":1,"lj":1,"ml":10,"ml2":{"a":0,"k":10,"ix":8},"nm":"Stroke 1","mn":"ADBE Vector Graphic - Stroke","hd":false},{"ty":"tr","p":{"a":0,"k":[0,0],"ix":2},"a":{"a":0,"k":[0,0],"ix":1},"s":{"a":0,"k":[100,100],"ix":3},"r":{"a":0,"k":0,"ix":6},"o":{"a":0,"k":100,"ix":7},"sk":{"a":0,"k":0,"ix":4},"sa":{"a":0,"k":0,"ix":5},"nm":"Transform"}],"nm":"Group 1","np":2,"cix":2,"ix":1,"mn":"ADBE Vector Group","hd":false}],"ip":0,"op":60.9999945377493,"st":0,"bm":0},{"ddd":0,"ind":34,"ty":4,"nm":"heartEffect","parent":37,"sr":1,"ks":{"o":{"a":0,"k":100,"ix":11},"r":{"a":0,"k":0,"ix":10},"p":{"a":0,"k":[28.486,-319.563,0],"ix":2},"a":{"a":0,"k":[28.486,-319.563,0],"ix":1},"s":{"a":0,"k":[100,100,100],"ix":6}},"ao":0,"shapes":[{"ty":"gr","it":[{"ind":0,"ty":"sh","ix":1,"ks":{"a":0,"k":{"i":[[9,-22],[-19.059,17.938]],"o":[[-9.103,22.252],[17,-16]],"v":[[17.5,-319.5],[37.5,-320.5]],"c":true},"ix":2},"nm":"Path 1","mn":"ADBE Vector Shape - Group","hd":false},{"ty":"fl","c":{"a":0,"k":[0.929411764706,0.117647058824,0.474509803922,1],"ix":4},"o":{"a":0,"k":100,"ix":5},"r":1,"nm":"Fill 1","mn":"ADBE Vector Graphic - Fill","hd":false},{"ty":"tr","p":{"a":0,"k":[0,0],"ix":2},"a":{"a":0,"k":[0,0],"ix":1},"s":{"a":0,"k":[100,100],"ix":3},"r":{"a":0,"k":0,"ix":6},"o":{"a":0,"k":100,"ix":7},"sk":{"a":0,"k":0,"ix":4},"sa":{"a":0,"k":0,"ix":5},"nm":"Transform"}],"nm":"Group 1","np":2,"cix":2,"ix":1,"mn":"ADBE Vector Group","hd":false}],"ip":0,"op":60.9999945377493,"st":0,"bm":0},{"ddd":0,"ind":35,"ty":4,"nm":"highLight1","parent":37,"sr":1,"ks":{"o":{"a":0,"k":100,"ix":11},"r":{"a":0,"k":0,"ix":10},"p":{"a":0,"k":[-96.536,-275.019,0],"ix":2},"a":{"a":0,"k":[-155.853,-221.548,0],"ix":1},"s":{"a":0,"k":[27.062,56.492,100],"ix":6}},"ao":0,"shapes":[{"ty":"gr","it":[{"ind":0,"ty":"sh","ix":1,"ks":{"a":0,"k":{"i":[[-4.44,12.581],[-3,-25]],"o":[[6,-17],[3,25]],"v":[[-128.5,-248.5],[-183.5,-196.5]],"c":true},"ix":2},"nm":"Path 1","mn":"ADBE Vector Shape - Group","hd":false},{"ty":"fl","c":{"a":0,"k":[1,1,1,1],"ix":4},"o":{"a":0,"k":100,"ix":5},"r":1,"nm":"Fill 1","mn":"ADBE Vector Graphic - Fill","hd":false},{"ty":"tr","p":{"a":0,"k":[0,0],"ix":2},"a":{"a":0,"k":[0,0],"ix":1},"s":{"a":0,"k":[100,100],"ix":3},"r":{"a":0,"k":0,"ix":6},"o":{"a":0,"k":100,"ix":7},"sk":{"a":0,"k":0,"ix":4},"sa":{"a":0,"k":0,"ix":5},"nm":"Transform"}],"nm":"Group 1","np":2,"cix":2,"ix":1,"mn":"ADBE Vector Group","hd":false}],"ip":0,"op":60.9999945377493,"st":0,"bm":0},{"ddd":0,"ind":36,"ty":4,"nm":"highLight2","parent":37,"sr":1,"ks":{"o":{"a":0,"k":100,"ix":11},"r":{"a":0,"k":0,"ix":10},"p":{"a":0,"k":[-112.2,-239.253,0],"ix":2},"a":{"a":0,"k":[-182.424,-158.011,0],"ix":1},"s":{"a":0,"k":[54.586,36.543,100],"ix":6}},"ao":0,"shapes":[{"ty":"gr","it":[{"ind":0,"ty":"sh","ix":1,"ks":{"a":0,"k":{"i":[[-15,-1],[11,-6]],"o":[[6.693,0.446],[0,0]],"v":[[-188.5,-173.5],[-175.5,-142.5]],"c":true},"ix":2},"nm":"Path 1","mn":"ADBE Vector Shape - Group","hd":false},{"ty":"fl","c":{"a":0,"k":[1,1,1,1],"ix":4},"o":{"a":0,"k":100,"ix":5},"r":1,"nm":"Fill 1","mn":"ADBE Vector Graphic - Fill","hd":false},{"ty":"tr","p":{"a":0,"k":[0,0],"ix":2},"a":{"a":0,"k":[0,0],"ix":1},"s":{"a":0,"k":[100,100],"ix":3},"r":{"a":0,"k":0,"ix":6},"o":{"a":0,"k":100,"ix":7},"sk":{"a":0,"k":0,"ix":4},"sa":{"a":0,"k":0,"ix":5},"nm":"Transform"}],"nm":"Group 1","np":2,"cix":2,"ix":1,"mn":"ADBE Vector Group","hd":false}],"ip":0,"op":60.9999945377493,"st":0,"bm":0},{"ddd":0,"ind":37,"ty":4,"nm":"heartBody","sr":1,"ks":{"o":{"a":0,"k":100,"ix":11},"r":{"a":1,"k":[{"i":{"x":[0.667],"y":[1]},"o":{"x":[0.333],"y":[0]},"n":["0p667_1_0p333_0"],"t":0,"s":[0],"e":[10]},{"i":{"x":[0.667],"y":[1]},"o":{"x":[0.333],"y":[0]},"n":["0p667_1_0p333_0"],"t":15,"s":[10],"e":[0]},{"i":{"x":[0.667],"y":[1]},"o":{"x":[0.333],"y":[0]},"n":["0p667_1_0p333_0"],"t":29,"s":[0],"e":[10]},{"i":{"x":[0.667],"y":[1]},"o":{"x":[0.333],"y":[0]},"n":["0p667_1_0p333_0"],"t":44,"s":[10],"e":[0]},{"t":59.9999946272944}],"ix":10},"p":{"s":true,"x":{"a":0,"k":280.639,"ix":3},"y":{"a":1,"k":[{"i":{"x":[0.667],"y":[1]},"o":{"x":[0.333],"y":[0]},"n":["0p667_1_0p333_0"],"t":0,"s":[360.972],"e":[225.972]},{"i":{"x":[0.667],"y":[1]},"o":{"x":[0.333],"y":[0]},"n":["0p667_1_0p333_0"],"t":15,"s":[225.972],"e":[360.972]},{"i":{"x":[0.667],"y":[1]},"o":{"x":[0.333],"y":[0]},"n":["0p667_1_0p333_0"],"t":29,"s":[360.972],"e":[225.972]},{"i":{"x":[0.667],"y":[1]},"o":{"x":[0.333],"y":[0]},"n":["0p667_1_0p333_0"],"t":44,"s":[225.972],"e":[360.972]},{"t":59.9999946272944}],"ix":4}},"a":{"a":0,"k":[10.639,-139.028,0],"ix":1},"s":{"a":1,"k":[{"i":{"x":[0.667,0.667,0.667],"y":[1,1,1]},"o":{"x":[0.333,0.333,0.333],"y":[0,0,0]},"n":["0p667_1_0p333_0","0p667_1_0p333_0","0p667_1_0p333_0"],"t":0,"s":[103,97,100],"e":[95,105,100]},{"i":{"x":[0.667,0.667,0.667],"y":[1,1,1]},"o":{"x":[0.333,0.333,0.333],"y":[0,0,0]},"n":["0p667_1_0p333_0","0p667_1_0p333_0","0p667_1_0p333_0"],"t":15,"s":[95,105,100],"e":[103,97,100]},{"i":{"x":[0.667,0.667,0.667],"y":[1,1,1]},"o":{"x":[0.333,0.333,0.333],"y":[0,0,0]},"n":["0p667_1_0p333_0","0p667_1_0p333_0","0p667_1_0p333_0"],"t":29,"s":[103,97,100],"e":[95,105,100]},{"i":{"x":[0.667,0.667,0.667],"y":[1,1,1]},"o":{"x":[0.333,0.333,0.333],"y":[0,0,0]},"n":["0p667_1_0p333_0","0p667_1_0p333_0","0p667_1_0p333_0"],"t":45,"s":[95,105,100],"e":[103,97,100]},{"t":59.9999946272944}],"ix":6}},"ao":0,"shapes":[{"ty":"gr","it":[{"ind":0,"ty":"sh","ix":1,"ks":{"a":0,"k":{"i":[[0,0],[37.875,46.704],[-65.906,49.031],[0,0],[-102.802,-11.406],[39.791,-59.257],[0,0],[48.5,0.981]],"o":[[0,0],[-69.062,-85.161],[120.732,-89.819],[0,0],[117.057,12.988],[-45.053,67.093],[0,0],[-48.5,-0.981]],"v":[[-14.063,27.984],[-113.153,-72.395],[-122.364,-291.449],[71.956,-228.242],[188.549,-330.686],[220.713,-75.619],[125.5,35.5],[45,49.481]],"c":true},"ix":2},"nm":"Path 1","mn":"ADBE Vector Shape - Group","hd":false},{"ty":"fl","c":{"a":0,"k":[0.929411764706,0.117647058824,0.474509803922,1],"ix":4},"o":{"a":0,"k":100,"ix":5},"r":1,"nm":"Fill 1","mn":"ADBE Vector Graphic - Fill","hd":false},{"ty":"tr","p":{"a":0,"k":[0,0],"ix":2},"a":{"a":0,"k":[0,0],"ix":1},"s":{"a":0,"k":[100,100],"ix":3},"r":{"a":0,"k":0,"ix":6},"o":{"a":0,"k":100,"ix":7},"sk":{"a":0,"k":0,"ix":4},"sa":{"a":0,"k":0,"ix":5},"nm":"Transform"}],"nm":"Group 1","np":2,"cix":2,"ix":1,"mn":"ADBE Vector Group","hd":false}],"ip":0,"op":60.9999945377493,"st":0,"bm":0}],"markers":[]}